pakm/__main__.py
pakm/constants.py
pakm/main.py
pakm-0.1.0.dist-info/LICENSE
pakm-0.1.0.dist-info/METADATA
pakm-0.1.0.dist-info/WHEEL
pakm-0.1.0.dist-info/entry_points.txt
pakm-0.1.0.dist-info/top_level.txt
pakm-0.1.0.dist-info/RECORD
